README.md
setup.py
realkd/__init__.py
realkd/datasets.py
realkd/evaluation.py
realkd/legacy.py
realkd/logic.py
realkd/patch.py
realkd/rules.py
realkd/search.py
realkd/subgroups.py
realkd.egg-info/PKG-INFO
realkd.egg-info/SOURCES.txt
realkd.egg-info/dependency_links.txt
realkd.egg-info/requires.txt
realkd.egg-info/top_level.txt
test/test_logic.py
test/test_rules.py
test/test_search.py
test/test_subgroups.py