Metadata-Version: 2.1
Name: realkd
Version: 0.2.0
Summary: Methods for knowledge discovery and interpretable machine learning.
Home-page: https://github.com/marioboley/realkd.py
Author: Mario Boley
Author-email: mario.boley@gmail.com
License: MIT
Platform: UNKNOWN
Classifier: Development Status :: 3 - Alpha
Classifier: License :: OSI Approved :: MIT License
Classifier: Programming Language :: Python :: 3
Requires-Python: >=3.6
